simms/__init__.py
simms/casasm.py
simms/config.json
simms/core.py
simms/observatories/__init__.py
simms/observatories/kat-7.itrf.txt
simms/observatories/lofar_nl.itrf.txt
simms/observatories/meerkat.itrf.txt
simms/observatories/skamid197.itrf.txt
simms/observatories/skamid254.itrf.txt
simms/observatories/vlaa.itrf.txt
simms/observatories/vlab.itrf.txt
simms/observatories/vlac.itrf.txt
simms/observatories/vlad.itrf.txt
simms/observatories/wsrt.itrf.txt
simms-2.0.1.dist-info/LICENSE
simms-2.0.1.dist-info/METADATA
simms-2.0.1.dist-info/WHEEL
simms-2.0.1.dist-info/entry_points.txt
simms-2.0.1.dist-info/RECORD
