Metadata-Version: 2.1
Name: simms
Version: 2.0.1
Summary: Empty MS creation tool
Home-page: https://github.com/radio-astro/simms
License: GPL2
Author: Sphesihle Makhathini
Author-email: sphemakh@gmail.com
Requires-Python: >=3.6,<4.0
Classifier: License :: Other/Proprietary License
Classifier: Programming Language :: Python :: 3
Classifier: Programming Language :: Python :: 3.6
Classifier: Programming Language :: Python :: 3.7
Classifier: Programming Language :: Python :: 3.8
Classifier: Programming Language :: Python :: 3.9
Classifier: Programming Language :: Python :: 3.10
Classifier: Programming Language :: Python :: 3.11
Classifier: Programming Language :: Python :: 3.12
Requires-Dist: casatasks (<6.6.3)
Requires-Dist: casatools (<6.6.3)
Requires-Dist: numpy (<2.0)
